README.md
background2.py
setup.py
background2.egg-info/PKG-INFO
background2.egg-info/SOURCES.txt
background2.egg-info/dependency_links.txt
background2.egg-info/requires.txt
background2.egg-info/top_level.txt